pyrinium/__init__.py
pyrinium/core.py
pyrinium/extractor.py
pyrinium/parser.py
pyrinium-0.0.8.dist-info/METADATA
pyrinium-0.0.8.dist-info/WHEEL
pyrinium-0.0.8.dist-info/licenses/LICENSE
pyrinium-0.0.8.dist-info/RECORD
