Metadata-Version: 2.4
Name: pyrinium
Version: 0.0.8
Summary: Parser for Sirius Universiry schedule
Project-URL: Homepage, https://github.com/PerovXP/pyrinium
Project-URL: Issues, https://github.com/PerovXP/pyrinium/issues
Author-email: Daniil Perov <perov@otso.city>
License-Expression: MIT
License-File: LICENSE
Classifier: Operating System :: OS Independent
Classifier: Programming Language :: Python :: 3
Requires-Python: >=3.9
Requires-Dist: requests
